Metadata-Version: 2.1
Name: gruut
Version: 2.1.1
Summary: A tokenizer, text cleaner, and phonemizer for many human languages.
Home-page: https://github.com/rhasspy/gruut
Author: Michael Hansen
Author-email: mike@rhasspy.org
License: UNKNOWN
Platform: UNKNOWN
Classifier: Programming Language :: Python :: 3
Classifier: Programming Language :: Python :: 3.6
Classifier: Programming Language :: Python :: 3.7
Classifier: Programming Language :: Python :: 3.8
Classifier: Programming Language :: Python :: 3.9
Classifier: License :: OSI Approved :: MIT License
Requires-Python: >=3.6
Provides-Extra: align
Provides-Extra: all
Provides-Extra: ar
Provides-Extra: cs
Provides-Extra: de
Provides-Extra: es
Provides-Extra: fa
Provides-Extra: fr
Provides-Extra: g2p
Provides-Extra: it
Provides-Extra: nl
Provides-Extra: pt
Provides-Extra: ru
Provides-Extra: sv
Provides-Extra: sw
Provides-Extra: train
